frontend/build/asset-manifest.json
frontend/build/index.html
frontend/build/robots.txt
frontend/build/static/css/main.95e38137.css
frontend/build/static/css/main.95e38137.css.map
frontend/build/static/favicon.ico
frontend/build/static/js/488.8edbc83a.chunk.js
frontend/build/static/js/488.8edbc83a.chunk.js.map
frontend/build/static/js/main.426cd4d4.js
frontend/build/static/js/main.426cd4d4.js.LICENSE.txt
frontend/build/static/js/main.426cd4d4.js.map
frontend/build/static/manifest.json
frontend/build/static/media/index.0054d71a83cfe9aa4a0c.cjs
frontend/build/static/media/index.d110dde2349866d5f780.cjs
frontend/build/static/media/index.d64cca1358b36db061fb.cjs
frontend/build/static/media/logo.e44efe3246aecc6d6219.png
sample_data/maintenance/input/setup_conda_mouse2p_image.tiff
sample_data/maintenance/output/setup_conda_caiman/experiment.yaml
sample_data/maintenance/output/setup_conda_caiman/snakemake.yaml
sample_data/maintenance/output/setup_conda_caiman/workflow.yaml
sample_data/maintenance/output/setup_conda_custom/experiment.yaml
sample_data/maintenance/output/setup_conda_custom/snakemake.yaml
sample_data/maintenance/output/setup_conda_custom/workflow.yaml
sample_data/maintenance/output/setup_conda_lccd/experiment.yaml
sample_data/maintenance/output/setup_conda_lccd/snakemake.yaml
sample_data/maintenance/output/setup_conda_lccd/workflow.yaml
sample_data/maintenance/output/setup_conda_optinist/experiment.yaml
sample_data/maintenance/output/setup_conda_optinist/snakemake.yaml
sample_data/maintenance/output/setup_conda_optinist/workflow.yaml
sample_data/maintenance/output/setup_conda_suite2p/experiment.yaml
sample_data/maintenance/output/setup_conda_suite2p/snakemake.yaml
sample_data/maintenance/output/setup_conda_suite2p/workflow.yaml
sample_data/tutorial/input/sample_mouse2p_behavior.csv
sample_data/tutorial/input/sample_mouse2p_image.tiff
sample_data/tutorial/output/tutorial1/experiment.yaml
sample_data/tutorial/output/tutorial1/snakemake.yaml
optinist-2.2.3.dist-info/LICENSE
optinist-2.2.3.dist-info/METADATA
optinist-2.2.3.dist-info/WHEEL
optinist-2.2.3.dist-info/entry_points.txt
optinist-2.2.3.dist-info/RECORD
