Metadata-Version: 2.3
Name: optinist
Version: 2.2.3
Summary: Calcium Imaging Pipeline Tool
License: GPL-3.0
Keywords: optinist
Author: OIST
Author-email: email@example.com
Requires-Python: >=3.9,<4.0
Classifier: Intended Audience :: Developers
Classifier: Intended Audience :: Education
Classifier: Intended Audience :: Science/Research
Classifier: License :: OSI Approved :: GNU General Public License v3 (GPLv3)
Classifier: Operating System :: MacOS :: MacOS X
Classifier: Operating System :: Microsoft :: Windows
Classifier: Operating System :: POSIX :: Linux
Classifier: Programming Language :: Python :: 3
Classifier: Programming Language :: Python :: 3.9
Classifier: Programming Language :: Python :: 3.10
Classifier: Programming Language :: Python :: 3.11
Classifier: Programming Language :: Python :: 3.12
Classifier: Programming Language :: Python :: 3.13
Classifier: Programming Language :: Python :: 3.8
Classifier: Topic :: Scientific/Engineering
Requires-Dist: aiofiles
Requires-Dist: alembic (==1.9.2)
Requires-Dist: concurrent-log-handler (>=0.9.25,<0.10.0)
Requires-Dist: fastapi (==0.104.*)
Requires-Dist: fastapi_pagination (==0.12.13)
Requires-Dist: filelock
Requires-Dist: firebase_admin
Requires-Dist: future
Requires-Dist: httpx (==0.21.0)
Requires-Dist: imageio
Requires-Dist: jinja2 (==3.1.*)
Requires-Dist: matplotlib (==3.7.*)
Requires-Dist: nbstripout
Requires-Dist: numpy (==1.24.3)
Requires-Dist: numpydoc
Requires-Dist: pandas (==1.5.3)
Requires-Dist: plotly (==5.18.0)
Requires-Dist: psutil
Requires-Dist: pydantic[dotenv,email] (==1.10.13)
Requires-Dist: pymatreader (>=0.0.32,<0.0.33)
Requires-Dist: pymysql (==1.1.0)
Requires-Dist: pynwb (==2.8.3)
Requires-Dist: pyrebase4 (==4.7.1)
Requires-Dist: python-jose[cryptography]
Requires-Dist: python-multipart
Requires-Dist: pyyaml
Requires-Dist: ruamel-yaml (>=0.18.5,<0.19.0)
Requires-Dist: snakemake (>=7.24,<7.31)
Requires-Dist: sqlmodel (==0.0.12)
Requires-Dist: starlette (==0.27.0)
Requires-Dist: tifffile
Requires-Dist: tqdm
Requires-Dist: uvicorn (==0.24.*)
Requires-Dist: xmltodict
Requires-Dist: yapf
Project-URL: Documentation, https://optinist.readthedocs.io
Project-URL: Repository, https://github.com/oist/optinist
